azure/mgmt/kubernetesconfiguration/extensiontypes/__init__.py
azure/mgmt/kubernetesconfiguration/extensiontypes/_configuration.py
azure/mgmt/kubernetesconfiguration/extensiontypes/_kubernetes_configuration_extension_types_mgmt_client.py
azure/mgmt/kubernetesconfiguration/extensiontypes/_patch.py
azure/mgmt/kubernetesconfiguration/extensiontypes/_version.py
azure/mgmt/kubernetesconfiguration/extensiontypes/py.typed
azure/mgmt/kubernetesconfiguration/extensiontypes/_utils/__init__.py
azure/mgmt/kubernetesconfiguration/extensiontypes/_utils/serialization.py
azure/mgmt/kubernetesconfiguration/extensiontypes/aio/__init__.py
azure/mgmt/kubernetesconfiguration/extensiontypes/aio/_configuration.py
azure/mgmt/kubernetesconfiguration/extensiontypes/aio/_kubernetes_configuration_extension_types_mgmt_client.py
azure/mgmt/kubernetesconfiguration/extensiontypes/aio/_patch.py
azure/mgmt/kubernetesconfiguration/extensiontypes/aio/operations/__init__.py
azure/mgmt/kubernetesconfiguration/extensiontypes/aio/operations/_extension_types_operations.py
azure/mgmt/kubernetesconfiguration/extensiontypes/aio/operations/_patch.py
azure/mgmt/kubernetesconfiguration/extensiontypes/models/__init__.py
azure/mgmt/kubernetesconfiguration/extensiontypes/models/_models_py3.py
azure/mgmt/kubernetesconfiguration/extensiontypes/models/_patch.py
azure/mgmt/kubernetesconfiguration/extensiontypes/operations/__init__.py
azure/mgmt/kubernetesconfiguration/extensiontypes/operations/_extension_types_operations.py
azure/mgmt/kubernetesconfiguration/extensiontypes/operations/_patch.py
azure_mgmt_kubernetesconfiguration_extensiontypes-1.0.0b1.dist-info/LICENSE
azure_mgmt_kubernetesconfiguration_extensiontypes-1.0.0b1.dist-info/METADATA
azure_mgmt_kubernetesconfiguration_extensiontypes-1.0.0b1.dist-info/WHEEL
azure_mgmt_kubernetesconfiguration_extensiontypes-1.0.0b1.dist-info/top_level.txt
azure_mgmt_kubernetesconfiguration_extensiontypes-1.0.0b1.dist-info/RECORD
